autocomplete_all/__init__.py
autocomplete_all/_version.py
autocomplete_all/autocomplete_all.py
autocomplete_all/static/autocomplete_all/js/autocomplete_all.js
autocomplete_all/templates/admin/base_site.html
django_admin_autocomplete_all-0.6.6.dist-info/AUTHORS.rst
django_admin_autocomplete_all-0.6.6.dist-info/LICENSE
django_admin_autocomplete_all-0.6.6.dist-info/METADATA
django_admin_autocomplete_all-0.6.6.dist-info/WHEEL
django_admin_autocomplete_all-0.6.6.dist-info/top_level.txt
django_admin_autocomplete_all-0.6.6.dist-info/RECORD
