Metadata-Version: 2.1
Name: django-admin-autocomplete-all
Version: 0.6.6
Summary: django admin: use select2 (autocomplete_fields) everywhere
Home-page: https://github.com/pyutil/django-admin-autocomplete-all
Download-URL: https://github.com/pyutil/django-admin-autocomplete-all/archive/0.6.6.tar.gz
Author: Mirek Zvolský
Author-email: zvolsky@seznam.cz
License: MIT
Keywords: django-admin-autocomplete-all
Classifier: Development Status :: 4 - Beta
Classifier: Framework :: Django :: 2.2
Classifier: Framework :: Django :: 3.1
Classifier: Intended Audience :: Developers
Classifier: License :: OSI Approved :: BSD License
Classifier: Natural Language :: English
Classifier: Programming Language :: Python :: 3
Classifier: Programming Language :: Python :: 3.7
Classifier: Programming Language :: Python :: 3.8
Classifier: Programming Language :: Python :: 3.9
License-File: LICENSE
License-File: AUTHORS.rst
